Metadata-Version: 1.0
Name: pam
Version: 0.1.1
Summary: PAM interface using ctypes
Home-page: http://atlee.ca/software/pam
Author: Chris AtLee
Author-email: chris@atlee.ca
License: MIT
Download-URL: http://atlee.ca/software/pam/dist/0.1.1
Platform: UNKNOWN
Classifier: Development Status :: 3 - Alpha
Classifier: Intended Audience :: Developers
Classifier: License :: OSI Approved :: MIT License
Classifier: Operating System :: POSIX :: Linux
Classifier: Programming Language :: Python
Classifier: Topic :: Software Development :: Libraries :: Python Modules
Classifier: Topic :: System :: Systems Administration :: Authentication/Directory
